<?xml version="1.0" encoding="UTF-8"?>
<npc name="Grizzly Adams" script="data/npc/scripts/default.lua" walkinterval="2000" floorchange="0">
<health now="100" max="100"/>
<look type="144" head="97" body="97" legs="94" feet="97" addons="3"/>
	 <parameters>
        <parameter key="message_greet" value="Welcome to my shop, adventurer |PLAYERNAME|! I {trade} with creature products."/>
        <parameter key="message_farewell" value="Good bye and come again, |PLAYERNAME|."/>
        <parameter key="module_keywords" value="1" />
        <parameter key="keywords" value="job;" />
        <parameter key="keyword_reply1" value="I am the hunting guide. If you want to begin a task, just ask." />
        <parameter key="module_shop" value="1"/>
        <parameter key="shop_sellable" value="hydra head,11199, 600"/>
    </parameters>
	
	
</npc>

